odoo/addons/account_cash_basis_group_base_line/README.rst
odoo/addons/account_cash_basis_group_base_line/__init__.py
odoo/addons/account_cash_basis_group_base_line/__manifest__.py
odoo/addons/account_cash_basis_group_base_line/i18n/account_cash_basis_group_base_line.pot
odoo/addons/account_cash_basis_group_base_line/models/__init__.py
odoo/addons/account_cash_basis_group_base_line/models/account_move.py
odoo/addons/account_cash_basis_group_base_line/readme/CONTRIBUTORS.rst
odoo/addons/account_cash_basis_group_base_line/readme/DESCRIPTION.rst
odoo/addons/account_cash_basis_group_base_line/readme/USAGE.rst
odoo/addons/account_cash_basis_group_base_line/static/description/icon.png
odoo/addons/account_cash_basis_group_base_line/static/description/index.html
odoo12_addon_account_cash_basis_group_base_line-12.0.0.0.1.99.dev5.dist-info/METADATA
odoo12_addon_account_cash_basis_group_base_line-12.0.0.0.1.99.dev5.dist-info/WHEEL
odoo12_addon_account_cash_basis_group_base_line-12.0.0.0.1.99.dev5.dist-info/top_level.txt
odoo12_addon_account_cash_basis_group_base_line-12.0.0.0.1.99.dev5.dist-info/RECORD
