Metadata-Version: 2.1
Name: odoo12-addon-account-cash-basis-group-base-line
Version: 12.0.0.0.1.99.dev5
Summary: Tax Cash Basis Group Base Lines
Home-page: https://github.com/OCA/account-financial-tools
Author: Vauxoo, Odoo Community Association (OCA)
Author-email: support@odoo-community.org
License: AGPL-3
Platform: UNKNOWN
Classifier: Programming Language :: Python
Classifier: Framework :: Odoo
Classifier: Framework :: Odoo :: 12.0
Classifier: License :: OSI Approved :: GNU Affero General Public License v3
Requires-Python: >=3.5
Requires-Dist: odoo <12.1dev,>=12.0a
